<Properties StartupConfiguration="{EF4C9FD7-B6D7-4D56-9410-6E30F1C886A3}|Default">
  <MonoDevelop.Ide.Workspace ActiveConfiguration="Debug" />
  <MonoDevelop.Ide.ItemProperties.MemoryGame PreferredExecutionTarget="MonoDevelop.Default" />
  <MonoDevelop.Ide.Workbench ActiveDocument="MemoryGame/MemoryGameApp.cs">
    <Files>
      <File FileName="MemoryGame/MemoryGameApp.cs" Line="36" Column="29" />
      <File FileName="CodeLouisvilleLibrary/CodeLouisvilleAppBase.cs" Line="297" Column="1" />
      <File FileName="MemoryGame/Program.cs" Line="1" Column="1" />
      <File FileName="GameLibrary/Words.cs" Line="1" Column="1" />
      <File FileName="GameLibrary/Player.cs" Line="1" Column="1" />
    </Files>
    <Pads>
      <Pad Id="ProjectPad">
        <State name="__root__">
          <Node name="MemoryGame" expanded="True">
            <Node name="CodeLouisvilleLibrary" expanded="True" />
            <Node name="GameLibrary" expanded="True" />
            <Node name="MemoryGame" expanded="True" />
          </Node>
        </State>
      </Pad>
      <Pad Id="MonoDevelop.Debugger.WatchPad">
        <State />
      </Pad>
    </Pads>
  </MonoDevelop.Ide.Workbench>
  <MonoDevelop.Ide.DebuggingService.Breakpoints>
    <BreakpointStore />
  </MonoDevelop.Ide.DebuggingService.Breakpoints>
  <MonoDevelop.Ide.DebuggingService.PinnedWatches />
  <MultiItemStartupConfigurations />
</Properties>